pybotics/__init__.py
pybotics/errors.py
pybotics/geometry.py
pybotics/json_encoder.py
pybotics/kinematic_chain.py
pybotics/link.py
pybotics/optimization.py
pybotics/predefined_models.py
pybotics/robot.py
pybotics/tool.py
pybotics-3.1.2.dist-info/LICENSE
pybotics-3.1.2.dist-info/METADATA
pybotics-3.1.2.dist-info/WHEEL
pybotics-3.1.2.dist-info/RECORD
